{
  "meta": {
    "description": "Bot-Hilfe anzeigen"
  },
  "name": "Hilfe",
  "support_server": "Support Server",
  "page1": {
    "title": "How to use the Bot",
    "description": "Wenn du den Bot in einer Antwort auf einer Nachricht erwähnst, generiert er ein Bild von dieser Nachricht.",
    "available_options": "Verfügbare Optionen",
    "separate": "Wenn du mehr als eine wählst, seperiere sie mit `,`",
    "font_name": "Schriftart Name"
  },
  "page4": {
    "title": "About Custom Quote",
    "description": "Custom Quote feature allows you to create a Quote from a fictitious statement.",
    "1": "Conditions of use",
    "2": "Both the creator and the recipient must allow custom quotes in the Web Dashboard.",
    "3": "Wie zu verwenden",
    "4": "Use the `/custom_quote` command. If `quote_as` is specified, the custom Quote will be created in the user's name, otherwise in your name."
  },
  "page5": {
    "title": "About Web Dashboard",
    "link": "You can access the dashboard from the URL above.",
    "description": "The dashboard allows customization of user and server settings.",
    "links": {
      "title": "Links",
      "home": "Top Page",
      "dashboard": "Dashboard",
      "status": "Bot status",
      "terms": "Terms of Service",
      "privacy": "Privacy Policy"
    }
  },
  "buttons": {
    "prev": "Vorherige",
    "next": "Weiter",
    "close": "Schließen"
  },
  "only_executor": "Only the user who invoked this help message can execute this action."
}
